axn/__init__.py
axn/attacks.py
axn/databases.py
axn/network.py
axn/pentest_tools.py
axn/reporting.py
axn/sniffing.py
axn/utils.py
axn/web.py
axn-0.1.dist-info/METADATA
axn-0.1.dist-info/WHEEL
axn-0.1.dist-info/top_level.txt
axn-0.1.dist-info/RECORD
