Metadata-Version: 2.4
Name: axn
Version: 0.1
Summary: A Python library for interacting with test network.
Home-page: https://github.com/Mahdy-Ahmadi/SXN
Download-URL: https://github.com/Mahdy-Ahmadi/SXN
Author: Mahdi Ahmadi
Author-email: mahdiahmadi.1208@gmail.com
Maintainer: Mahdi Ahmadi
Maintainer-email: mahdiahmadi.1208@gmail.com
Classifier: Programming Language :: Python :: 3
Classifier: License :: OSI Approved :: MIT License
Classifier: Operating System :: OS Independent
Classifier: Topic :: Communications :: Chat
Classifier: Topic :: Software Development :: Libraries
Requires-Python: >=3.6
Requires-Dist: requests
Requires-Dist: Pillow
Requires-Dist: websocket-client
Requires-Dist: pycryptodome
Requires-Dist: aiohttp
Requires-Dist: tqdm
Requires-Dist: mutagen
Requires-Dist: filetype
Requires-Dist: aiofiles
Dynamic: author
Dynamic: author-email
Dynamic: classifier
Dynamic: description-content-type
Dynamic: download-url
Dynamic: home-page
Dynamic: maintainer
Dynamic: maintainer-email
Dynamic: requires-dist
Dynamic: requires-python
Dynamic: summary
